gfp/__init__.py
gfp/__main__.py
gfp/example.py
gfp/py.typed
gfp/typer.py
gfp-0.1.4.dist-info/METADATA
gfp-0.1.4.dist-info/WHEEL
gfp-0.1.4.dist-info/entry_points.txt
gfp-0.1.4.dist-info/top_level.txt
gfp-0.1.4.dist-info/RECORD
