Metadata-Version: 2.1
Name: gfp
Version: 0.1.4
Summary: Python CLI for gforien.
Author: gforien
Project-URL: Homepage, https://github.com/gforien/gfp
Requires-Python: >=3.10
Requires-Dist: typer ==0.12.5
Provides-Extra: build
Requires-Dist: gfp[build-template] ; extra == 'build'
Provides-Extra: build-template
Requires-Dist: build[virtualenv] ==1.0.3 ; extra == 'build-template'
Provides-Extra: dev
Requires-Dist: gfp[tox] ; extra == 'dev'
Requires-Dist: gfp[lint] ; extra == 'dev'
Requires-Dist: gfp[test] ; extra == 'dev'
Requires-Dist: gfp[doc] ; extra == 'dev'
Requires-Dist: gfp[build] ; extra == 'dev'
Provides-Extra: doc
Requires-Dist: gfp[doc-template] ; extra == 'doc'
Provides-Extra: doc-template
Requires-Dist: sphinx ==7.2.6 ; extra == 'doc-template'
Requires-Dist: sphinx-rtd-theme ==1.3.0 ; extra == 'doc-template'
Requires-Dist: sphinx-autodoc-typehints ==1.24.0 ; extra == 'doc-template'
Requires-Dist: pip-licenses ==4.3.2 ; extra == 'doc-template'
Requires-Dist: jinja2 ==3.1.2 ; extra == 'doc-template'
Provides-Extra: lint
Requires-Dist: gfp[lint-template] ; extra == 'lint'
Provides-Extra: lint-template
Requires-Dist: mypy ==1.5.1 ; extra == 'lint-template'
Requires-Dist: pytest ==7.4.1 ; extra == 'lint-template'
Requires-Dist: types-docutils ; extra == 'lint-template'
Requires-Dist: types-setuptools ; extra == 'lint-template'
Requires-Dist: jinja2 ==3.1.2 ; extra == 'lint-template'
Requires-Dist: ruff ==0.1.6 ; extra == 'lint-template'
Provides-Extra: test
Requires-Dist: gfp[test-template] ; extra == 'test'
Provides-Extra: test-template
Requires-Dist: pytest ==7.4.1 ; extra == 'test-template'
Requires-Dist: pytest-randomly ==3.15.0 ; extra == 'test-template'
Requires-Dist: pytest-cov ==4.1.0 ; extra == 'test-template'
Requires-Dist: coverage[toml] ==7.3.1 ; extra == 'test-template'
Provides-Extra: tox
Requires-Dist: tox ==4.11.1 ; extra == 'tox'
